[
  {
    "id": "6024967931",
    "source": "realty_in_us",
    "address": "6240 Woodsman Dr",
    "city": "Zephyrhills",
    "state": "FL",
    "zip": "33544",
    "region": "Tampa Bay",
    "price": 212900,
    "priceFormatted": "212,900",
    "beds": 3,
    "baths": 2,
    "sqft": 1080,
    "lotSize": 27443,
    "yearBuilt": null,
    "propertyType": "mobile",
    "listingStatus": "for_sale",
    "daysOnMarket": 0,
    "mlsNumber": null,
    "listingId": "2983231504",
    "image": "https://ap.rdcpix.com/c4f4cd8a8a1836660836b8e133231cafl-m3383361948s.jpg",
    "images": [],
    "listingUrl": "https://www.realtor.com/realestateandhomes-detail/6240-Woodsman-Dr_Zephyrhills_FL_33544_M60249-67931",
    "virtualTourUrl": "https://www.propertypanorama.com/instaview/stellar/W7876576",
    "description": "",
    "photoCount": 11,
    "tags": [],
    "hasGarage": false,
    "hasPool": false,
    "slug": "6240-woodsman-dr-wesley-chapel",
    "metaTitle": "6240 Woodsman Dr - Wesley Chapel, FL - $212,900",
    "metaDescription": "3 bed, 2 bath home in Wesley Chapel. 1080 sqft. Listed at $212,900.",
    "scrapedAt": "2025-11-17T22:24:00.285Z",
    "lastUpdated": "2025-11-17T22:24:00.285Z"
  },
  {
    "id": "5416254653",
    "source": "realty_in_us",
    "address": "26931 Deacon Loop",
    "city": "Zephyrhills",
    "state": "FL",
    "zip": "33544",
    "region": "Tampa Bay",
    "price": 229899,
    "priceFormatted": "229,899",
    "beds": 3,
    "baths": 2,
    "sqft": 1344,
    "lotSize": 50965,
    "yearBuilt": null,
    "propertyType": "mobile",
    "listingStatus": "for_sale",
    "daysOnMarket": 0,
    "mlsNumber": null,
    "listingId": "2983263849",
    "image": "https://ap.rdcpix.com/75e4213608a9df7f8550d9d6aa29dc67l-m3677980699s.jpg",
    "images": [],
    "listingUrl": "https://www.realtor.com/realestateandhomes-detail/26931-Deacon-Loop_Zephyrhills_FL_33544_M54162-54653",
    "virtualTourUrl": "https://www.propertypanorama.com/instaview/stellar/W7876592",
    "description": "",
    "photoCount": 16,
    "tags": [],
    "hasGarage": false,
    "hasPool": false,
    "slug": "26931-deacon-loop-wesley-chapel",
    "metaTitle": "26931 Deacon Loop - Wesley Chapel, FL - $229,899",
    "metaDescription": "3 bed, 2 bath home in Wesley Chapel. 1344 sqft. Listed at $229,899.",
    "scrapedAt": "2025-11-17T22:24:00.285Z",
    "lastUpdated": "2025-11-17T22:24:00.285Z"
  },
  {
    "id": "5496979041",
    "source": "realty_in_us",
    "address": "Address not available",
    "city": "Zephyrhills",
    "state": "FL",
    "zip": "33544",
    "region": "Tampa Bay",
    "price": 450000,
    "priceFormatted": "450,000",
    "beds": 0,
    "baths": 0,
    "sqft": 0,
    "lotSize": 435600,
    "yearBuilt": null,
    "propertyType": "land",
    "listingStatus": "for_sale",
    "daysOnMarket": 0,
    "mlsNumber": null,
    "listingId": "548857674",
    "image": "https://ap.rdcpix.com/934f3adc9f521584dd4b2ae83ffcadcbl-m652962577s.jpg",
    "images": [],
    "listingUrl": "https://www.realtor.com/realestateandhomes-detail/Zephyrhills_FL_33544_M54969-79041",
    "virtualTourUrl": null,
    "description": "",
    "photoCount": 6,
    "tags": [],
    "hasGarage": false,
    "hasPool": false,
    "slug": "property-1763418240285",
    "metaTitle": "Home - Wesley Chapel, FL - $450,000",
    "metaDescription": "0 bed, 0 bath home in Wesley Chapel. 0 sqft. Listed at $450,000.",
    "scrapedAt": "2025-11-17T22:24:00.285Z",
    "lastUpdated": "2025-11-17T22:24:00.285Z"
  }
]